{"nodes": [{"id": "sections_home_hero_homehero", "label": "HomeHero", "file_type": "code", "source_file": "src/components/sections/home-hero.tsx", "source_location": null, "source_url": null, "captured_at": null, "author": null, "contributor": null}], "edges": [{"source": "sections_home_hero_homehero", "target": "sections_cta_link_ctalink", "relation": "calls", "confidence": "EXTRACTED", "confidence_score": 1.0, "source_file": "src/components/sections/home-hero.tsx", "source_location": null, "weight": 1.0}, {"source": "sections_home_hero_homehero", "target": "sections_google_reviews_googlereviewbadge", "relation": "calls", "confidence": "EXTRACTED", "confidence_score": 1.0, "source_file": "src/components/sections/home-hero.tsx", "source_location": null, "weight": 1.0}, {"source": "sections_home_hero_homehero", "target": "sections_lead_form_leadform", "relation": "references", "confidence": "INFERRED", "confidence_score": 0.75, "source_file": "src/components/sections/home-hero.tsx", "source_location": null, "weight": 1.0}], "hyperedges": [{"id": "hero_component_family", "label": "Dark ink hero components with rise animation and CTA", "nodes": ["sections_home_hero_homehero", "sections_page_hero_pagehero", "sections_cta_link_ctalink", "sections_google_reviews_googlereviewbadge"], "relation": "form", "confidence": "INFERRED", "confidence_score": 0.85, "source_file": "src/components/sections/home-hero.tsx"}]}